odoo/addons/stock_picking_filter_lot/README.rst
odoo/addons/stock_picking_filter_lot/__init__.py
odoo/addons/stock_picking_filter_lot/__manifest__.py
odoo/addons/stock_picking_filter_lot/i18n/it.po
odoo/addons/stock_picking_filter_lot/i18n/stock_picking_filter_lot.pot
odoo/addons/stock_picking_filter_lot/models/__init__.py
odoo/addons/stock_picking_filter_lot/models/stock_production_lot.py
odoo/addons/stock_picking_filter_lot/readme/CONTRIBUTORS.rst
odoo/addons/stock_picking_filter_lot/readme/DESCRIPTION.rst
odoo/addons/stock_picking_filter_lot/readme/USAGE.rst
odoo/addons/stock_picking_filter_lot/static/description/icon.png
odoo/addons/stock_picking_filter_lot/static/description/index.html
odoo/addons/stock_picking_filter_lot/views/stock_move_line_view.xml
odoo/addons/stock_picking_filter_lot/views/stock_picking_view.xml
odoo11_addon_stock_picking_filter_lot-11.0.1.0.0.99.dev7.dist-info/METADATA
odoo11_addon_stock_picking_filter_lot-11.0.1.0.0.99.dev7.dist-info/WHEEL
odoo11_addon_stock_picking_filter_lot-11.0.1.0.0.99.dev7.dist-info/top_level.txt
odoo11_addon_stock_picking_filter_lot-11.0.1.0.0.99.dev7.dist-info/RECORD
